lib/Config.py
lib/__init__.py
lib/asgi.py
lib/grant_callback.py
lib/grant_redirect.py
lib/logging_file.py
lib/oauth_utils.py
lib/pass_token.py
lib/pass_userinfo.py
lib/settings.py
lib/urls.py
lib/wsgi.py
oauth_django-0.0.3.dist-info/LICENSE.txt
oauth_django-0.0.3.dist-info/METADATA
oauth_django-0.0.3.dist-info/WHEEL
oauth_django-0.0.3.dist-info/top_level.txt
oauth_django-0.0.3.dist-info/RECORD
