Metadata-Version: 2.1
Name: oauth_django
Version: 0.0.3
Summary: A package for handling Xecurify authentication
Author: Romit
Author-email: romitaherkar@gmail.com
Classifier: Framework :: Django
Classifier: Programming Language :: Python :: 3
Classifier: License :: OSI Approved :: MIT License
Classifier: Operating System :: OS Independent
License-File: LICENSE.txt
Requires-Dist: Django
Requires-Dist: cryptography
Requires-Dist: pyjwt
Requires-Dist: django
